timetool/__init__.py
timetool/main.py
timetool-0.12.dist-info/METADATA
timetool-0.12.dist-info/WHEEL
timetool-0.12.dist-info/entry_points.txt
timetool-0.12.dist-info/RECORD
