Metadata-Version: 2.4
Name: timetool
Version: 0.12
Summary: Quick timezone and time format conversion CLI tool
Project-URL: Homepage, https://github.com/personalcomputer/timetool
Author-email: John Miller <john@johngm.com>
Classifier: License :: OSI Approved :: MIT License
Classifier: Programming Language :: Python
Classifier: Programming Language :: Python :: 3
Classifier: Programming Language :: Python :: Implementation :: CPython
Requires-Python: >=3.7.0
Requires-Dist: babel
Requires-Dist: natural>=0.2.0
Requires-Dist: python-dateutil
Requires-Dist: pytz
Requires-Dist: tzdata
